Metadata-Version: 1.0
Name: WizCoin
Version: 0.0.1
Summary: WizCoin is a module for handling wizard currency.
Home-page: https://github.com/asweigart/wizcoin
Author: Al Sweigart
Author-email: al@inventwithpython.com
License: BSD
Keywords: wizard currency galleon sickle knut
Platform: UNKNOWN
